LICENSE
MANIFEST.in
README.md
setup.py
message_media_lookups/__init__.py
message_media_lookups/api_helper.py
message_media_lookups/configuration.py
message_media_lookups/decorators.py
message_media_lookups/message_media_lookups_client.py
message_media_lookups/controllers/__init__.py
message_media_lookups/controllers/base_controller.py
message_media_lookups/controllers/lookups_controller.py
message_media_lookups/exceptions/__init__.py
message_media_lookups/exceptions/api_exception.py
message_media_lookups/http/__init__.py
message_media_lookups/http/http_call_back.py
message_media_lookups/http/http_client.py
message_media_lookups/http/http_context.py
message_media_lookups/http/http_method_enum.py
message_media_lookups/http/http_request.py
message_media_lookups/http/http_response.py
message_media_lookups/http/requests_client.py
message_media_lookups/http/auth/__init__.py
message_media_lookups/http/auth/basic_auth.py
message_media_lookups/models/__init__.py
message_media_lookups/models/lookup_a_phone_number_response.py
messagemedia_lookups_sdk.egg-info/PKG-INFO
messagemedia_lookups_sdk.egg-info/SOURCES.txt
messagemedia_lookups_sdk.egg-info/dependency_links.txt
messagemedia_lookups_sdk.egg-info/requires.txt
messagemedia_lookups_sdk.egg-info/top_level.txt
tests/__init__.py
tests/http_response_catcher.py
tests/test_helper.py
tests/controllers/__init__.py
tests/controllers/controller_test_base.py
tests/controllers/test_lookups_controller.py