Metadata-Version: 1.0
Name: messagemedia-lookups-sdk
Version: 1.0.1
Summary: The MessageMedia Lookups API provides a number of endpoints for validating the phone numbers you're sending to by checking their validity, type and carrier records.
Home-page: https://developers.messagemedia.com
Author: MessageMedia Developers
Author-email: developers@messagemedia.com
License: UNKNOWN
Platform: UNKNOWN
